Workbook

Sheet Synthèse
A1: Hôpital de campagne – Synthèse du chiffrage informatique et réseau
A2: Projet étudiant. Prix HT estimés 2025-2026 (à confirmer par devis). Budget de la première année : achats + installation + 12 mois de services.
A4: Poste | B4: Montant HT | C4: Part du total HT | D4: Source
A5: Total matériel | B5: =Matériel!G33 -> 12475 | C5: =IF($B$14=0,0,B5/$B$14) -> 0.2345035 | D5: Onglet Matériel
A6: Total logiciels | B6: ='Logiciels et licences'!H21 -> 1000 | C6: =IF($B$14=0,0,B6/$B$14) -> 0.018797876 | D6: Onglet Logiciels et licences
A7: Total licences | B7: ='Logiciels et licences'!H20 -> 2400 | C7: =IF($B$14=0,0,B7/$B$14) -> 0.045114902 | D7: CAL Windows Server
A8: Total abonnements (12 mois) | B8: =Abonnements!G12 -> 8535 | C8: =IF($B$14=0,0,B8/$B$14) -> 0.16043987 | D8: Onglet Abonnements
A9: Total sécurité | B9: =Sécurité!H20 -> 1800 | C9: =IF($B$14=0,0,B9/$B$14) -> 0.033836177 | D9: Onglet Sécurité
A10: Total supervision | B10: =Supervision!H11 -> 130 | C10: =IF($B$14=0,0,B10/$B$14) -> 0.0024437239 | D10: Onglet Supervision
A11: Total maintenance | B11: =Maintenance!H14 -> 2290 | C11: =IF($B$14=0,0,B11/$B$14) -> 0.043047136 | D11: Onglet Maintenance
A12: Installation et main d'œuvre | B12: =Installation!F11 -> 21200 | C12: =IF($B$14=0,0,B12/$B$14) -> 0.39851497 | D12: Onglet Installation
A13: Aléas | B13: =Hypothèses!$B$11*(B5+B12) -> 3367.5 | C13: =IF($B$14=0,0,B13/$B$14) -> 0.063301847 | D13: % sur matériel + installation
A14: TOTAL HT | B14: =SUM(B5:B13) -> 53197.5 | C14: =IF($B$14=0,0,B14/$B$14) -> 1
A15: TVA | B15: =B14*Hypothèses!$B$5 -> 10639.5 | D15: Taux défini dans Hypothèses
A16: TOTAL TTC | B16: =B14+B15 -> 63837
A18: Coûts récurrents annuels (années suivantes)
A19: Renouvellement des logiciels | B19: ='Logiciels et licences'!I19 -> 0
A20: Abonnements (12 mois) | B20: =Abonnements!E12 -> 8535
A21: Sécurité (renouvellements) | B21: =Sécurité!I20 -> 270
A22: Supervision (récurrent) | B22: =Supervision!I11 -> 0
A23: Maintenance (récurrent) | B23: =Maintenance!I14 -> 1000
A24: TOTAL RÉCURRENT ANNUEL HT | B24: =SUM(B19:B23) -> 9805
A25: TOTAL RÉCURRENT ANNUEL TTC | B25: =B24*(1+Hypothèses!$B$5) -> 11766
A27: Indicateurs complémentaires
A28: Amortissement annuel du matériel (HT) | B28: =Matériel!K33 -> 2335.9286 | D28: Information : matériel / durée d'amortissement
A29: Projection sur 3 ans (HT) | B29: =B14+2*B24 -> 72807.5 | D29: Année 1 + 2 années de coûts récurrents
A30: Projection sur 3 ans (TTC) | B30: =B29*(1+Hypothèses!$B$5) -> 87369
A31: Mise en service du réseau interne (semaines, max) | B31: =Planning!J11 -> 9.2 | D31: Onglet Planning
A32: Mise en service complète, tous liens (semaines, max) | B32: =Planning!J12 -> 12 | D32: Limitée par l'Orange FTTO

Sheet Matériel
A1: Matériel
A2: Prix HT estimés (2025-2026). Jaune = option ou champ à compléter (quantité 0). Pare-feu, NAS, extension mémoire et pièces de rechange sont comptés dans Sécurité, Supervision et Maintenance.
A4: Catégorie | B4: Équipement | C4: Marque | D4: Modèle | E4: Quantité | F4: Prix unitaire HT | G4: Total HT | H4: Durée d'amortissement (ans) | I4: Rôle | J4: Remarques | K4: Amortissement annuel HT | L4: Statut du prix
A5: Réseau | B5: Routeur OSPF (cœur et distribution) | C5: MikroTik | D5: RB5009UG+S+IN | E5: 6 | F5: 220 | G5: =E5*F5 -> 1320 | H5: 5 | I5: Routage OSPF, VRRP entre les LAN | J5: 6 routeurs identiques : maintenance simplifiée | K5: =G5/H5 -> 264 | L5: Estimation
A6: Réseau | B6: Switch L2 WAN (3 liens) | C6: TP-Link | D6: Omada SG2210P | E6: 1 | F6: 100 | G6: =E6*F6 -> 100 | H6: 5 | I6: Reçoit FTTO, Free et 5G (VLAN 10/20/30) | J6: Alternative : TL-SG108E | K6: =G6/H6 -> 20 | L6: Estimation
A7: Réseau | B7: Switch L2 côté firewall | C7: Cisco | D7: CBS350-24T-4G | E7: 1 | F7: 450 | G7: =E7*F7 -> 450 | H7: 7 | I7: Distribution côté pare-feu | J7: 4 ports SFP | K7: =G7/H7 -> 64.285714 | L7: Estimation
A8: Réseau | B8: Switch L2 LAN 5 (serveurs) | C8: Cisco | D8: CBS350-24T-4G | E8: 1 | F8: 450 | G8: =E8*F8 -> 450 | H8: 7 | I8: Raccorde les 4 serveurs | J8: SFP en liaison montante | K8: =G8/H8 -> 64.285714 | L8: Estimation
A9: Réseau | B9: Switch L2 PoE LAN 1, 2 et 3 | C9: Cisco | D9: CBS250-24PP-4G | E9: 3 | F9: 330 | G9: =E9*F9 -> 990 | H9: 7 | I9: Accès salle d'opération, labo, hall ; alimente bornes, téléphone, capteur | J9: PoE+ 100 W | K9: =G9/H9 -> 141.42857 | L9: Estimation
A10: Réseau | B10: Switch L2 PoE LAN 4 (chambre) | C10: Cisco | D10: CBS250-8PP-D | E10: 1 | F10: 150 | G10: =E10*F10 -> 150 | H10: 7 | I10: Accès chambre, téléphone IP | J10: Sans ventilateur (silencieux) | K10: =G10/H10 -> 21.428571 | L10: Estimation
A11: Réseau | B11: Borne Wi-Fi | C11: Ubiquiti | D11: UniFi U6 Pro | E11: 2 | F11: 160 | G11: =E11*F11 -> 320 | H11: 5 | I11: Wi-Fi 6 LAN 2 et LAN 3, roaming 802.11r/k/v | J11: Alternative : TP-Link EAP650 | K11: =G11/H11 -> 64 | L11: Estimation
A12: Réseau | B12: Module SFP 1G (liaisons montantes fibre) | C12: Compatible Cisco/MikroTik | D12: SFP 1000BASE-SX | E12: 4 | F12: 40 | G12: =E12*F12 -> 160 | H12: 5 | I12: Liaisons fibre entre locaux si nécessaire | J12: HYPOTHÈSE : à confirmer selon les distances | K12: =G12/H12 -> 32 | L12: Estimation
A13: Réseau | B13: Routeur 5G (lien de secours) | C13: Teltonika | D13: RUTX50 | E13: 1 | F13: 400 | G13: =E13*F13 -> 400 | H13: 5 | I13: Lien de secours VLAN 30 | J13: Cité dans le PDF des liens ; ONT Orange/Free fournis par les opérateurs | K13: =G13/H13 -> 80 | L13: Estimation
A14: Serveurs | B14: Serveur AD / DHCP / DNS (.1) | C14: Dell | D14: PowerEdge T150 (sans OS) | E14: 1 | F14: 750 | G14: =E14*F14 -> 750 | H14: 5 | I14: Annuaire, DHCP, DNS, fichiers, impression | J14: Xeon E-2300, 16 Go ECC, 2 disques RAID 1 ; OS compté dans Logiciels | K14: =G14/H14 -> 150 | L14: Estimation
A15: Serveurs | B15: Serveur WEB / BDD (.2) | C15: Dell | D15: PowerEdge T150 | E15: 1 | F15: 1000 | G15: =E15*F15 -> 1000 | H15: 5 | I15: Application web (3000), MariaDB (3306), hyperviseur des VM de supervision | J15: Mémoire portée à 32 Go (voir Supervision) | K15: =G15/H15 -> 200 | L15: Estimation
A16: Serveurs | B16: Serveur MQTT / Node-RED (.3) | C16: Intel | D16: NUC 13 Pro | E16: 1 | F16: 450 | G16: =E16*F16 -> 450 | H16: 4 | I16: Mosquitto 1883/8883, Node-RED 1880 | J16: Alternative : Raspberry Pi 5 (≈ 100 €) | K16: =G16/H16 -> 112.5 | L16: Estimation
... A18: Postes et périphériques | B18: Poste informatique accueil | C18: Dell | D18: OptiPlex 3000 Micro | E18: 2 | F18: 550 | G18: =E18*F18 -> 1100 | H18: 4 | I18: Postes du hall d'accueil (LAN 3) | J18: Windows 11 Pro inclus | K18: =G18/H18 -> 275 | L18: Estimation
A19: Postes et périphériques | B19: Écran 24" | C19: Dell | D19: P2425H | E19: 2 | F19: 140 | G19: =E19*F19 -> 280 | H19: 5 | I19: Écrans des 2 postes d'accueil | K19: =G19/H19 -> 56 | L19: Estimation
A20: Postes et périphériques | B20: Postes utilisateurs supplémentaires | C20: Dell | D20: OptiPlex 3000 Micro | E20: =Hypothèses!$B$14 -> 0 | F20: 550 | G20: =E20*F20 -> 0 | H20: 4 | I20: Postes complémentaires éventuels | J20: À COMPLÉTER (0 par défaut) | K20: =G20/H20 -> 0 | L20: Estimation
A21: Postes et périphériques | B21: Imprimante laser réseau | C21: HP | D21: LaserJet Pro M404dn | E21: 2 | F21: 280 | G21: =E21*F21 -> 560 | H21: 5 | I21: Impression via le serveur Windows (.1) | J21: AJOUT DEMANDÉ ; emplacement à définir ; IP réservée en DHCP | K21: =G21/H21 -> 112 | L21: Estimation
A22: Postes et périphériques | B22: Téléphone IP | C22: Yealink | D22: SIP-T31P | E22: 2 | F22: 50 | G22: =E22*F22 -> 100 | H22: 4 | I22: Téléphonie SIP (LAN 3 et LAN 4) | J22: PoE, 2 ports gigabit | K22: =G22/H22 -> 25 | L22: Estimation
A23: Postes et périphériques | B23: Capteur MQTT (MQTTS) | C23: Milesight / Shelly | D23: Passerelle capteur MQTT TLS | E23: 1 | F23: 80 | G23: =E23*F23 -> 80 | H23: 5 | I23: Publie en MQTT sur TLS (LAN 3) | J23: Modèle exact à choisir | K23: =G23/H23 -> 16 | L23: Estimation
A24: Baies et câblage | B24: Baie 19" 18U (local technique) | C24: Digitus ou équivalent | D24: Baie 18U 600 mm | E24: 1 | F24: 450 | G24: =E24*F24 -> 450 | H24: 10 | I24: Héberge routeurs, switchs, serveurs | J24: À retirer si une baie existe déjà | K24: =G24/H24 -> 45 | L24: Estimation
A25: Baies et câblage | B25: Coffret mural 19" 9U | C25: Digitus ou équivalent | D25: Coffret 9U | E25: 4 | F25: 150 | G25: =E25*F25 -> 600 | H25: 10 | I25: Switchs des LAN 1 à 4 | J25: À retirer si existant | K25: =G25/H25 -> 60 | L25: Estimation
A26: Baies et câblage | B26: Panneau de brassage 24 ports Cat6 | C26: Digitus ou équivalent | D26: 24 ports RJ45 Cat6 | E26: 5 | F26: 55 | G26: =E26*F26 -> 275 | H26: 10 | I26: Brassage des liaisons | K26: =G26/H26 -> 27.5 | L26: Estimation
A27: Baies et câblage | B27: Cordon de brassage RJ45 Cat6 | C27: Générique | D27: 0,5 à 2 m | E27: 60 | F27: 4 | G27: =E27*F27 -> 240 | H27: 5 | I27: Liens switchs, routeurs, serveurs | K27: =G27/H27 -> 48 | L27: Estimation
A28: Baies et câblage | B28: Bloc multiprises rackable (PDU) | C28: Générique | D28: PDU 19" 8 prises | E28: 5 | F28: 40 | G28: =E28*F28 -> 200 | H28: 8 | I28: Alimentation des baies | K28: =G28/H28 -> 25 | L28: Estimation
A29: Baies et câblage | B29: Accessoires (passe-câbles, vis, étiquettes) | C29: Divers | D29: Forfait | E29: 1 | F29: 100 | G29: =E29*F29 -> 100 | H29: 5 | I29: Finitions de baie | K29: =G29/H29 -> 20 | L29: Estimation
A30: Alimentation | B30: Onduleur rack 1500 VA | C30: APC | D30: Smart-UPS SMT1500RMI2U | E30: 1 | F30: 650 | G30: =E30*F30 -> 650 | H30: 5 | I30: Protège serveurs et cœur de réseau | J30: Batteries à remplacer tous les 3 à 5 ans | K30: =G30/H30 -> 130 | L30: Estimation
A31: Alimentation | B31: Onduleur 1000 VA | C31: APC | D31: Back-UPS BX1000MI | E31: 3 | F31: 150 | G31: =E31*F31 -> 450 | H31: 5 | I31: Protège les switchs des LAN 1 à 4 | J31: Couverture partielle (à compléter) | K31: =G31/H31 -> 90 | L31: Estimation
A32: Outillage | B32: Outillage réseau et PC de maintenance (lot) | C32: Divers | D32: Lot | E32: 1 | F32: 400 | G32: =E32*F32 -> 400 | H32: 5 | I32: Testeur de câbles, câbles console, outils | J32: Estimation globale | K32: =G32/H32 -> 80 | L32: Estimation
A33: TOTAL MATÉRIEL | G33: =SUM(G5:G32) -> 12475 | K33: =SUM(K5:K32) -> 2335.9286
A35: Sous-totaux par catégorie | G35: Total HT
A36: Réseau | G36: =SUMIF($A$5:$A$32,A36,$G$5:$G$32) -> 4340
A37: Serveurs | G37: =SUMIF($A$5:$A$32,A37,$G$5:$G$32) -> 2650
A38: Postes et périphériques | G38: =SUMIF($A$5:$A$32,A38,$G$5:$G$32) -> 2120
A39: Baies et câblage | G39: =SUMIF($A$5:$A$32,A39,$G$5:$G$32) -> 1865
A40: Alimentation | G40: =SUMIF($A$5:$A$32,A40,$G$5:$G$32) -> 1100
A41: Outillage | G41: =SUMIF($A$5:$A$32,A41,$G$5:$G$32) -> 400

Sheet Logiciels et licences
A1: Logiciels et licences
A2: Logiciels de sécurité, supervision et sauvegarde : voir onglets Sécurité et Supervision. Jaune = option (quantité 0).
A4: Catégorie | B4: Logiciel | C4: Éditeur | D4: Type de licence | E4: Quantité | F4: Durée | G4: Prix unitaire HT | H4: Total HT | I4: Renouvellement annuel HT | J4: Fonction / utilité | K4: Statut du prix
A5: Système d'exploitation | B5: Windows Server 2022 Standard | C5: Microsoft | D5: Perpétuelle (OEM) | E5: 1 | F5: Perpétuelle | G5: 1000 | H5: =E5*G5 -> 1000 | I5: 0 | J5: Serveur .1 : AD, DHCP, DNS, fichiers, impression | K5: Estimation
A6: Système d'exploitation | B6: Windows 11 Pro | C6: Microsoft | D6: OEM (inclus avec le PC) | E6: =Matériel!E18 -> 2 | F6: Perpétuelle | G6: 0 | H6: =E6*G6 -> 0 | I6: 0 | J6: Système des postes d'accueil, jonction au domaine AD | K6: Gratuit / inclus
A7: Système d'exploitation | B7: Debian 12 / Ubuntu Server 24.04 LTS | C7: Debian / Canonical | D7: Libre (GPL) | E7: 4 | F7: Illimitée | G7: 0 | H7: =E7*G7 -> 0 | I7: 0 | J7: VM WEB/BDD, VM supervision, VM journaux, serveur MQTT | K7: Gratuit / inclus
A8: Système d'exploitation | B8: FreePBX / Asterisk | C8: Sangoma (open source) | D8: Libre (GPL) | E8: 1 | F8: Illimitée | G8: 0 | H8: =E8*G8 -> 0 | I8: 0 | J8: Téléphonie SIP interne (serveur .4) | K8: Gratuit / inclus
A9: Virtualisation | B9: Proxmox VE | C9: Proxmox Server Solutions | D9: Libre (AGPL) | E9: 1 | F9: Illimitée | G9: 0 | H9: =E9*G9 -> 0 | I9: 0 | J9: Hyperviseur sur le serveur .2 (VM web/BDD, Zabbix, Wazuh) | K9: Gratuit / inclus
A10: Licences d'accès | B10: CAL utilisateur Windows Server 2022 | C10: Microsoft | D10: Licence d'accès (par utilisateur) | E10: =Hypothèses!$B$6 -> 50 | F10: Perpétuelle | G10: 48 | H10: =E10*G10 -> 2400 | I10: 0 | J10: Droit d'accès des utilisateurs à l'AD, aux fichiers et à l'impression | K10: Estimation
A11: Gestion des utilisateurs | B11: Active Directory Domain Services + GPO | C11: Microsoft | D11: Inclus avec Windows Server | E11: 1 | F11: Perpétuelle | G11: 0 | H11: =E11*G11 -> 0 | I11: 0 | J11: Comptes, groupes, droits, stratégies de sécurité | K11: Gratuit / inclus
A12: Gestion des équipements | B12: GLPI | C12: Teclib' / open source | D12: Libre (GPL) | E12: 1 | F12: Illimitée | G12: 0 | H12: =E12*G12 -> 0 | I12: 0 | J12: Inventaire des équipements et gestion des tickets | K12: Gratuit / inclus
A13: Gestion des équipements | B13: UniFi Network Application | C13: Ubiquiti | D13: Gratuit (contrôleur logiciel) | E13: 1 | F13: Illimitée | G13: 0 | H13: =E13*G13 -> 0 | I13: 0 | J13: Gestion centralisée des bornes Wi-Fi et du roaming | K13: Gratuit / inclus
A14: Services applicatifs | B14: MariaDB | C14: MariaDB Foundation | D14: Libre (GPL) | E14: 1 | F14: Illimitée | G14: 0 | H14: =E14*G14 -> 0 | I14: 0 | J14: Base de données (port 3306) | K14: Gratuit / inclus
A15: Services applicatifs | B15: Application web du projet (port 3000) | C15: Projet (interne) | D15: Développement interne | E15: 1 | F15: Illimitée | G15: 0 | H15: =E15*G15 -> 0 | I15: 0 | J15: Application web de l'hôpital | K15: Gratuit / inclus
A16: Services applicatifs | B16: Eclipse Mosquitto | C16: Eclipse Foundation | D16: Libre (EPL) | E16: 1 | F16: Illimitée | G16: 0 | H16: =E16*G16 -> 0 | I16: 0 | J16: Broker MQTT / MQTTS (1883 / 8883) | K16: Gratuit / inclus
A17: Services applicatifs | B17: Node-RED | C17: OpenJS Foundation | D17: Libre (Apache 2.0) | E17: 1 | F17: Illimitée | G17: 0 | H17: =E17*G17 -> 0 | I17: 0 | J17: Flux de données IoT (1880) | K17: Gratuit / inclus
A18: Bureautique | B18: LibreOffice | C18: The Document Foundation | D18: Libre (MPL) | E18: 2 | F18: Illimitée | G18: 0 | H18: =E18*G18 -> 0 | I18: 0 | J18: Bureautique des postes d'accueil | K18: Gratuit / inclus
A19: TOTAL | H19: =SUM(H5:H18) -> 3400 | I19: =SUM(I5:I18) -> 0
A20: dont licences d'accès (CAL) | H20: =SUMIF($A$5:$A$18,"Licences d'accès",$H$5:$H$18) -> 2400
A21: dont logiciels | H21: =H19-H20 -> 1000
A22: Option : Microsoft 365 (SaaS) : voir onglet Abonnements

Sheet Abonnements
A1: Abonnements et services
A2: Coût mensuel = quantité × prix unitaire mensuel. Coût total = coût annuel × durée / 12. Jaune = option (quantité 0). Liens Internet : document fourni.
A4: Service | B4: Fournisseur | C4: Type d'abonnement | D4: Coût mensuel HT | E4: Coût annuel HT | F4: Durée (mois) | G4: Coût total HT | H4: Quantité | I4: Prix unitaire mensuel HT | J4: Conditions particulières | K4: Statut du prix
A5: Fibre dédiée FTTO (VLAN 10) | B5: Orange Business | C5: Fibre entreprise, GTR 4 h | D5: =H5*I5 -> 600 | E5: =D5*12 -> 7200 | F5: 12 | G5: =E5*F5/12 -> 7200 | H5: 1 | I5: =Hypothèses!$B$12 -> 600 | J5: Débit symétrique, rétablissement en 4 h. Fourchette du document : 300 à 1 700 €/mois. | K5: Estimation (fourchette fournie)
A6: Fibre Free Pro (VLAN 20) | B6: Free Pro | C6: Freebox Pro, fibre mutualisée | D6: =H6*I6 -> 40 | E6: =D6*12 -> 480 | F6: 12 | G6: =E6*F6/12 -> 480 | H6: 1 | I6: 40 | J6: Sans garantie de rétablissement ; installation à confirmer auprès de Free. | K6: Document fourni
A7: 5G data pro double SIM (VLAN 30) | B7: Opérateur mobile (à choisir) | C7: Forfait data pro 5G | D7: =H7*I7 -> 40 | E7: =D7*12 -> 480 | F7: 12 | G7: =E7*F7/12 -> 480 | H7: 1 | I7: 40 | J7: Lien de secours ; fourchette du document : 20 à 60 €/mois. | K7: Estimation (fourchette fournie)
A8: Téléphonie externe (trunk SIP) | B8: Opérateur VoIP (à choisir) | C8: Trunk SIP, 2 canaux | D8: =H8*I8 -> 20 | E8: =D8*12 -> 240 | F8: 12 | G8: =E8*F8/12 -> 240 | H8: 2 | I8: 10 | J8: HYPOTHÈSE : mettre la quantité à 0 si la téléphonie reste interne. | K8: Estimation
A9: Sauvegarde externalisée 1 To | B9: Synology C2 ou Backblaze B2 | C9: Stockage cloud | D9: =H9*I9 -> 10 | E9: =D9*12 -> 120 | F9: 12 | G9: =E9*F9/12 -> 120 | H9: 1 | I9: 10 | J9: Copie hors site (règle 3-2-1). | K9: Estimation
A10: Nom de domaine | B10: Registrar (à choisir) | C10: Annuel (15 € HT/an) | D10: =H10*I10 -> 1.25 | E10: =D10*12 -> 15 | F10: 12 | G10: =E10*F10/12 -> 15 | H10: 1 | I10: 1.25 | J10: Certificats TLS via Let's Encrypt (gratuit). | K10: Estimation
A11: Microsoft 365 (SaaS) – option | B11: Microsoft | C11: Par utilisateur et par mois | D11: =H11*I11 -> 0 | E11: =D11*12 -> 0 | F11: 12 | G11: =E11*F11/12 -> 0 | H11: 0 | I11: 12.5 | J11: OPTION : mettre la quantité au nombre d'utilisateurs pour l'inclure. | K11: Estimation
A12: TOTAL | D12: =SUM(D5:D11) -> 711.25 | E12: =SUM(E5:E11) -> 8535 | G12: =SUM(G5:G11) -> 8535

Sheet Sécurité
A1: Sécurité
A2: Équipements et logiciels de sécurité. Jaune = option (quantité 0). Prix HT estimés.
A4: Catégorie | B4: Élément | C4: Marque / Éditeur | D4: Nature | E4: Quantité | F4: Prix unitaire HT | G4: Périodicité | H4: Total année 1 HT | I4: Récurrent annuel HT | J4: Rôle / remarques | K4: Statut du prix
A5: Pare-feu | B5: Pare-feu OPNsense (appliance) | C5: Deciso | D5: Matériel | E5: 1 | F5: 900 | G5: Une fois | H5: =E5*F5 -> 900 | I5: =IF(G5="Par an",E5*F5,0) -> 0 | J5: DEC740 : routage, IDS/IPS, VPN, Radius, portail captif ; bascule des 3 liens | K5: Estimation
A6: Pare-feu | B6: OPNsense Community Edition | C6: Deciso (open source) | D6: Logiciel | E6: 1 | F6: 0 | G6: Une fois | H6: =E6*F6 -> 0 | I6: =IF(G6="Par an",E6*F6,0) -> 0 | J6: Pare-feu, Suricata (IDS/IPS), portail captif, plugin FreeRADIUS | K6: Gratuit / inclus
A7: Pare-feu | B7: OPNsense Business Edition – option | C7: Deciso | D7: Logiciel | E7: 0 | F7: 150 | G7: Par an | H7: =E7*F7 -> 0 | I7: =IF(G7="Par an",E7*F7,0) -> 0 | J7: OPTION : support et mises à jour commerciales ; prix à confirmer | K7: Estimation
A8: Segmentation réseau / VLAN | B8: VLAN et ACL (LAN 1 à 5 + VLAN WAN 10/20/30) | C8: Cisco / MikroTik / OPNsense | D8: Configuration | E8: 1 | F8: 0 | G8: Une fois | H8: =E8*F8 -> 0 | I8: =IF(G8="Par an",E8*F8,0) -> 0 | J8: Un VLAN par LAN du diagramme ; plan VLAN définitif à compléter | K8: Gratuit / inclus
A9: VPN | B9: VPN IPsec / WireGuard (inclus OPNsense) | C9: Deciso | D9: Logiciel | E9: 1 | F9: 0 | G9: Une fois | H9: =E9*F9 -> 0 | I9: =IF(G9="Par an",E9*F9,0) -> 0 | J9: Accès distant des administrateurs | K9: Gratuit / inclus
A10: Contrôle d'accès | B10: 802.1X / RADIUS (FreeRADIUS) et portail captif | C10: Deciso / FreeRADIUS | D10: Logiciel | E10: 1 | F10: 0 | G10: Une fois | H10: =E10*F10 -> 0 | I10: =IF(G10="Par an",E10*F10,0) -> 0 | J10: Authentification des bornes et des invités | K10: Gratuit / inclus
A11: Authentification | B11: Active Directory + GPO (inclus Windows Server) | C11: Microsoft | D11: Logiciel | E11: 1 | F11: 0 | G11: Une fois | H11: =E11*F11 -> 0 | I11: =IF(G11="Par an",E11*F11,0) -> 0 | J11: Comptes, droits, mots de passe, stratégies (coût dans Logiciels) | K11: Gratuit / inclus
A12: Antivirus / EDR | B12: ESET PROTECT Entry (ou équivalent) | C12: ESET | D12: Logiciel | E12: =Hypothèses!$B$16 -> 6 | F12: 45 | G12: Par an | H12: =E12*F12 -> 270 | I12: =IF(G12="Par an",E12*F12,0) -> 270 | J12: Antivirus/EDR serveurs et postes ; renouvellement annuel | K12: Estimation
A13: Sauvegarde | B13: NAS Synology DS224+ | C13: Synology | D13: Matériel | E13: 1 | F13: 330 | G13: Une fois | H13: =E13*F13 -> 330 | I13: =IF(G13="Par an",E13*F13,0) -> 0 | J13: Cible de sauvegarde locale | K13: Estimation
A14: Sauvegarde | B14: Disque NAS 6 To (RAID 1) | C14: Seagate IronWolf | D14: Matériel | E14: 2 | F14: 150 | G14: Une fois | H14: =E14*F14 -> 300 | I14: =IF(G14="Par an",E14*F14,0) -> 0 | J14: Stockage des sauvegardes | K14: Estimation
A15: Sauvegarde | B15: Active Backup for Business | C15: Synology | D15: Logiciel | E15: 1 | F15: 0 | G15: Une fois | H15: =E15*F15 -> 0 | I15: =IF(G15="Par an",E15*F15,0) -> 0 | J15: Sauvegarde des serveurs et des postes, incluse avec le NAS | K15: Gratuit / inclus
A16: Journalisation et détection | B16: Wazuh (SIEM / XDR open source) | C16: Wazuh | D16: Logiciel | E16: 1 | F16: 0 | G16: Une fois | H16: =E16*F16 -> 0 | I16: =IF(G16="Par an",E16*F16,0) -> 0 | J16: Centralisation des journaux et détection d'incidents (VM sur serveur .2) | K16: Gratuit / inclus
A17: Protection des données | B17: Chiffrement (BitLocker, TLS/MQTTS) et certificats Let's Encrypt | C17: Microsoft / Let's Encrypt | D17: Logiciel | E17: 1 | F17: 0 | G17: Une fois | H17: =E17*F17 -> 0 | I17: =IF(G17="Par an",E17*F17,0) -> 0 | J17: Données au repos et en transit | K17: Gratuit / inclus
A18: Options | B18: Audit de sécurité / test d'intrusion – option | C18: Prestataire (à choisir) | D18: Service | E18: 0 | F18: 3000 | G18: Une fois | H18: =E18*F18 -> 0 | I18: =IF(G18="Par an",E18*F18,0) -> 0 | J18: OPTION : utile si le réseau traite des données de santé | K18: Estimation
A19: Options | B19: Assurance cyber – option | C19: Assureur (à choisir) | D19: Service | E19: 0 | F19: 1000 | G19: Par an | H19: =E19*F19 -> 0 | I19: =IF(G19="Par an",E19*F19,0) -> 0 | J19: OPTION : fourchette indicative 500 à 2 000 €/an | K19: Estimation
A20: TOTAL | H20: =SUM(H5:H19) -> 1800 | I20: =SUM(I5:I19) -> 270
A22: Sous-totaux par catégorie | H22: Total année 1 HT | I22: Récurrent annuel HT
A23: Pare-feu | H23: =SUMIF($A$5:$A$19,A23,$H$5:$H$19) -> 900 | I23: =SUMIF($A$5:$A$19,A23,$I$5:$I$19) -> 0
A24: Segmentation réseau / VLAN | H24: =SUMIF($A$5:$A$19,A24,$H$5:$H$19) -> 0 | I24: =SUMIF($A$5:$A$19,A24,$I$5:$I$19) -> 0
A25: VPN | H25: =SUMIF($A$5:$A$19,A25,$H$5:$H$19) -> 0 | I25: =SUMIF($A$5:$A$19,A25,$I$5:$I$19) -> 0
A26: Contrôle d'accès | H26: =SUMIF($A$5:$A$19,A26,$H$5:$H$19) -> 0 | I26: =SUMIF($A$5:$A$19,A26,$I$5:$I$19) -> 0
A27: Authentification | H27: =SUMIF($A$5:$A$19,A27,$H$5:$H$19) -> 0 | I27: =SUMIF($A$5:$A$19,A27,$I$5:$I$19) -> 0
A28: Antivirus / EDR | H28: =SUMIF($A$5:$A$19,A28,$H$5:$H$19) -> 270 | I28: =SUMIF($A$5:$A$19,A28,$I$5:$I$19) -> 270
A29: Sauvegarde | H29: =SUMIF($A$5:$A$19,A29,$H$5:$H$19) -> 630 | I29: =SUMIF($A$5:$A$19,A29,$I$5:$I$19) -> 0
A30: Journalisation et détection | H30: =SUMIF($A$5:$A$19,A30,$H$5:$H$19) -> 0 | I30: =SUMIF($A$5:$A$19,A30,$I$5:$I$19) -> 0
A31: Protection des données | H31: =SUMIF($A$5:$A$19,A31,$H$5:$H$19) -> 0 | I31: =SUMIF($A$5:$A$19,A31,$I$5:$I$19) -> 0
A32: Options | H32: =SUMIF($A$5:$A$19,A32,$H$5:$H$19) -> 0 | I32: =SUMIF($A$5:$A$19,A32,$I$5:$I$19) -> 0

Sheet Supervision
A1: Supervision
A2: Supervision, alertes, journaux et performances. Prix HT estimés.
A4: Catégorie | B4: Élément | C4: Marque / Éditeur | D4: Nature | E4: Quantité | F4: Prix unitaire HT | G4: Périodicité | H4: Total année 1 HT | I4: Récurrent annuel HT | J4: Rôle / remarques | K4: Statut du prix
A5: Supervision réseau et serveurs | B5: Zabbix 7.0 LTS (SNMP + agents) | C5: Zabbix (open source) | D5: Logiciel | E5: 1 | F5: 0 | G5: Une fois | H5: =E5*F5 -> 0 | I5: =IF(G5="Par an",E5*F5,0) -> 0 | J5: VM sur le serveur .2 : supervision routeurs, switchs, bornes, serveurs | K5: Gratuit / inclus
A6: Surveillance des équipements | B6: Sondes SNMP / ICMP sur les équipements réseau | C6: Zabbix | D6: Configuration | E6: 1 | F6: 0 | G6: Une fois | H6: =E6*F6 -> 0 | I6: =IF(G6="Par an",E6*F6,0) -> 0 | J6: Inclus dans Zabbix | K6: Gratuit / inclus
A7: Alertes | B7: Alertes Zabbix par e-mail / messagerie | C7: Zabbix | D7: Configuration | E7: 1 | F7: 0 | G7: Une fois | H7: =E7*F7 -> 0 | I7: =IF(G7="Par an",E7*F7,0) -> 0 | J7: Déclencheurs sur panne de lien, équipement ou service | K7: Gratuit / inclus
A8: Centralisation des journaux | B8: Syslog vers Wazuh | C8: Wazuh | D8: Logiciel | E8: 1 | F8: 0 | G8: Une fois | H8: =E8*F8 -> 0 | I8: =IF(G8="Par an",E8*F8,0) -> 0 | J8: Voir onglet Sécurité (coût déjà compté) | K8: Gratuit / inclus
A9: Gestion des performances | B9: Grafana OSS | C9: Grafana Labs (open source) | D9: Logiciel | E9: 1 | F9: 0 | G9: Une fois | H9: =E9*F9 -> 0 | I9: =IF(G9="Par an",E9*F9,0) -> 0 | J9: Tableaux de bord de performance alimentés par Zabbix | K9: Gratuit / inclus
A10: Capacité d'hébergement | B10: Extension mémoire serveur .2 (16 → 32 Go ECC) | C10: Dell | D10: Matériel | E10: 1 | F10: 130 | G10: Une fois | H10: =E10*F10 -> 130 | I10: =IF(G10="Par an",E10*F10,0) -> 0 | J10: Héberge les VM Zabbix et Wazuh à côté de la VM WEB/BDD | K10: Estimation
A11: TOTAL | H11: =SUM(H5:H10) -> 130 | I11: =SUM(I5:I10) -> 0
A13: Sous-totaux par catégorie | H13: Total année 1 HT | I13: Récurrent annuel HT
A14: Supervision réseau et serveurs | H14: =SUMIF($A$5:$A$10,A14,$H$5:$H$10) -> 0 | I14: =SUMIF($A$5:$A$10,A14,$I$5:$I$10) -> 0
A15: Surveillance des équipements | H15: =SUMIF($A$5:$A$10,A15,$H$5:$H$10) -> 0 | I15: =SUMIF($A$5:$A$10,A15,$I$5:$I$10) -> 0
A16: Alertes | H16: =SUMIF($A$5:$A$10,A16,$H$5:$H$10) -> 0 | I16: =SUMIF($A$5:$A$10,A16,$I$5:$I$10) -> 0
A17: Centralisation des journaux | H17: =SUMIF($A$5:$A$10,A17,$H$5:$H$10) -> 0 | I17: =SUMIF($A$5:$A$10,A17,$I$5:$I$10) -> 0
A18: Gestion des performances | H18: =SUMIF($A$5:$A$10,A18,$H$5:$H$10) -> 0 | I18: =SUMIF($A$5:$A$10,A18,$I$5:$I$10) -> 0
A19: Capacité d'hébergement | H19: =SUMIF($A$5:$A$10,A19,$H$5:$H$10) -> 130 | I19: =SUMIF($A$5:$A$10,A19,$I$5:$I$10) -> 0

Sheet Maintenance
A1: Maintenance
A2: Contrats, garanties, support et stock de remplacement. Jaune = option (quantité 0).
A4: Catégorie | B4: Élément | C4: Marque / Éditeur | D4: Nature | E4: Quantité | F4: Prix unitaire HT | G4: Périodicité | H4: Total année 1 HT | I4: Récurrent annuel HT | J4: Rôle / remarques | K4: Statut du prix
A5: Support constructeur | B5: Dell ProSupport Next Business Day, 3 ans (serveurs T150) | C5: Dell | D5: Service | E5: 2 | F5: 250 | G5: Une fois | H5: =E5*F5 -> 500 | I5: =IF(G5="Par an",E5*F5,0) -> 0 | J5: Intervention J+1 ; renouvellement au bout de 3 ans | K5: Estimation
A6: Garantie | B6: Garantie Cisco CBS250/350 (limitée à vie, incluse) | C6: Cisco | D6: Garantie | E6: 1 | F6: 0 | G6: Une fois | H6: =E6*F6 -> 0 | I6: =IF(G6="Par an",E6*F6,0) -> 0 | J6: Incluse à l'achat | K6: Gratuit / inclus
A7: Garantie | B7: Garanties constructeur MikroTik, TP-Link, Ubiquiti, Yealink, Deciso | C7: Divers | D7: Garantie | E7: 1 | F7: 0 | G7: Une fois | H7: =E7*F7 -> 0 | I7: =IF(G7="Par an",E7*F7,0) -> 0 | J7: Incluses ; durées à confirmer auprès de chaque fabricant | K7: Gratuit / inclus
A8: Maintenance | B8: Contrat de maintenance / infogérance de base | C8: Prestataire (à choisir) | D8: Service | E8: 1 | F8: 1000 | G8: Par an | H8: =E8*F8 -> 1000 | I8: =IF(G8="Par an",E8*F8,0) -> 1000 | J8: Estimation ; astreinte et interventions à définir | K8: Estimation
A9: Maintenance logicielle | B9: Mises à jour (WSUS inclus Windows Server, apt, OPNsense) | C9: Divers | D9: Logiciel | E9: 1 | F9: 0 | G9: Une fois | H9: =E9*F9 -> 0 | I9: =IF(G9="Par an",E9*F9,0) -> 0 | J9: Processus interne, fenêtres de maintenance planifiées | K9: Gratuit / inclus
A10: Remplacement du matériel | B10: Switch CBS250-24PP-4G de secours | C10: Cisco | D10: Matériel | E10: 1 | F10: 330 | G10: Une fois | H10: =E10*F10 -> 330 | I10: =IF(G10="Par an",E10*F10,0) -> 0 | J10: Stock de remplacement immédiat | K10: Estimation
A11: Remplacement du matériel | B11: Routeur RB5009 de secours | C11: MikroTik | D11: Matériel | E11: 1 | F11: 220 | G11: Une fois | H11: =E11*F11 -> 220 | I11: =IF(G11="Par an",E11*F11,0) -> 0 | J11: Stock de remplacement immédiat | K11: Estimation
A12: Remplacement du matériel | B12: SSD de secours pour serveurs | C12: Divers | D12: Matériel | E12: 2 | F12: 120 | G12: Une fois | H12: =E12*F12 -> 240 | I12: =IF(G12="Par an",E12*F12,0) -> 0 | J12: Remplacement rapide d'un disque du RAID 1 | K12: Estimation
A13: Options | B13: Abonnement Proxmox VE (support) – option | C13: Proxmox Server Solutions | D13: Service | E13: 0 | F13: 115 | G13: Par an | H13: =E13*F13 -> 0 | I13: =IF(G13="Par an",E13*F13,0) -> 0 | J13: OPTION : prix à confirmer | K13: Estimation
A14: TOTAL | H14: =SUM(H5:H13) -> 2290 | I14: =SUM(I5:I13) -> 1000
A16: Sous-totaux par catégorie | H16: Total année 1 HT | I16: Récurrent annuel HT
A17: Support constructeur | H17: =SUMIF($A$5:$A$13,A17,$H$5:$H$13) -> 500 | I17: =SUMIF($A$5:$A$13,A17,$I$5:$I$13) -> 0
A18: Garantie | H18: =SUMIF($A$5:$A$13,A18,$H$5:$H$13) -> 0 | I18: =SUMIF($A$5:$A$13,A18,$I$5:$I$13) -> 0
A19: Maintenance | H19: =SUMIF($A$5:$A$13,A19,$H$5:$H$13) -> 1000 | I19: =SUMIF($A$5:$A$13,A19,$I$5:$I$13) -> 1000
A20: Maintenance logicielle | H20: =SUMIF($A$5:$A$13,A20,$H$5:$H$13) -> 0 | I20: =SUMIF($A$5:$A$13,A20,$I$5:$I$13) -> 0
A21: Remplacement du matériel | H21: =SUMIF($A$5:$A$13,A21,$H$5:$H$13) -> 790 | I21: =SUMIF($A$5:$A$13,A21,$I$5:$I$13) -> 0
A22: Options | H22: =SUMIF($A$5:$A$13,A22,$H$5:$H$13) -> 0 | I22: =SUMIF($A$5:$A$13,A22,$I$5:$I$13) -> 0

Sheet Installation
A1: Installation et main d'œuvre
A2: Bâtiment existant : câblage et génie civil intérieur déjà faits. Génie civil extérieur exclu.
A4: Poste | B4: Type | C4: Quantité | D4: Unité | E4: Tarif unitaire HT | F4: Total HT | G4: Remarque
A5: Montage physique des équipements | B5: Main d'œuvre | C5: 2 | D5: jours | E5: =Hypothèses!$B$10 -> 450 | F5: =C5*E5 -> 900 | G5: Fixation en baie, brassage, étiquetage
A6: Configuration des équipements | B6: Main d'œuvre | C6: 22 | D6: jours | E6: =Hypothèses!$B$9 -> 650 | F6: =C6*E6 -> 14300 | G6: Pare-feu, routeurs OSPF/VRRP, switchs, Wi-Fi, serveurs, postes, imprimantes
A7: Supervision, sauvegarde et sécurité | B7: Main d'œuvre | C7: 2 | D7: jours | E7: =Hypothèses!$B$9 -> 650 | F7: =C7*E7 -> 1300 | G7: Zabbix, Wazuh, Active Backup, EDR
A8: Gestion de projet et recette | B8: Main d'œuvre | C8: 3 | D8: jours | E8: =Hypothèses!$B$9 -> 650 | F8: =C8*E8 -> 1950 | G8: Coordination, documentation, tests finaux
A9: Formation du personnel | B9: Prestation | C9: 1 | D9: forfait | E9: 1000 | F9: =C9*E9 -> 1000 | G9: Prise en main du portail captif, de la téléphonie et des procédures de panne
A10: Frais d'installation des liens Internet | B10: Opérateurs | C10: 1 | D10: forfait | E10: =Hypothèses!$B$13 -> 1750 | F10: =C10*E10 -> 1750 | G10: Fourchette du document fourni : 0 à 3 500 €
A11: TOTAL INSTALLATION | F11: =SUM(F5:F10) -> 21200
A12: dont main d'œuvre (jours facturés) | F12: =SUM(F5:F8) -> 18450

Sheet Planning
A1: Planning estimé
A2: Durées en jours ouvrés. Configuration = charge (jours-homme) divisée par l'effectif défini dans Hypothèses.
A4: N° | B4: Phase | C4: Durée min (j) | D4: Durée max (j) | E4: Début min (j) | F4: Fin min (j) | G4: Début max (j) | H4: Fin max (j) | I4: Fin min (sem) | J4: Fin max (sem) | K4: Remarque
A5: 1 | B5: Étude et commandes (plan IP/VLAN, devis, commandes) | C5: 5 | D5: 10 | E5: =0 -> 0 | F5: =E5+C5 -> 5 | G5: =0 -> 0 | H5: =G5+D5 -> 10 | I5: =F5/Hypothèses!$B$8 -> 1 | J5: =H5/Hypothèses!$B$8 -> 2 | K5: Commander les liens en priorité.
A6: 2 | B6: Livraison du matériel | C6: 5 | D6: 15 | E6: =F5 -> 5 | F6: =E6+C6 -> 10 | G6: =H5 -> 10 | H6: =G6+D6 -> 25 | I6: =F6/Hypothèses!$B$8 -> 2 | J6: =H6/Hypothèses!$B$8 -> 5 | K6: Selon le stock du revendeur.
A7: 3 | B7: Raccordement des liens Internet | C7: 10 | D7: 60 | E7: =0 -> 0 | F7: =E7+C7 -> 10 | G7: =0 -> 0 | H7: =G7+D7 -> 60 | I7: =F7/Hypothèses!$B$8 -> 2 | J7: =H7/Hypothèses!$B$8 -> 12 | K7: 5G en quelques jours, Free 2 à 6 sem., Orange FTTO 4 à 12 sem.
A8: 4 | B8: Montage physique | C8: =Installation!$C$5 -> 2 | D8: =Installation!$C$5 -> 2 | E8: =F6 -> 10 | F8: =E8+C8 -> 12 | G8: =H6 -> 25 | H8: =G8+D8 -> 27 | I8: =F8/Hypothèses!$B$8 -> 2.4 | J8: =H8/Hypothèses!$B$8 -> 5.4 | K8: Dès réception du matériel.
A9: 5 | B9: Configuration (réseau, serveurs, supervision, sauvegarde) | C9: =(Installation!$C$6+Installation!$C$7)/Hypothèses!$B$7 -> 12 | D9: =(Installation!$C$6+Installation!$C$7)/Hypothèses!$B$7 -> 12 | E9: =F8 -> 12 | F9: =E9+C9 -> 24 | G9: =H8 -> 27 | H9: =G9+D9 -> 39 | I9: =F9/Hypothèses!$B$8 -> 4.8 | J9: =H9/Hypothèses!$B$8 -> 7.8 | K9: Charge en jours-homme / effectif.
A10: 6 | B10: Tests et recette | C10: 3 | D10: 5 | E10: =F9 -> 24 | F10: =E10+C10 -> 27 | G10: =H9 -> 39 | H10: =G10+D10 -> 44 | I10: =F10/Hypothèses!$B$8 -> 5.4 | J10: =H10/Hypothèses!$B$8 -> 8.8 | K10: Bascule des liens, roaming, VRRP, sauvegardes.
A11: 7 | B11: Mise en service interne et prise en main | C11: 1 | D11: 2 | E11: =F10 -> 27 | F11: =E11+C11 -> 28 | G11: =H10 -> 44 | H11: =G11+D11 -> 46 | I11: =F11/Hypothèses!$B$8 -> 5.6 | J11: =H11/Hypothèses!$B$8 -> 9.2 | K11: Réseau interne sur 5G/Free si Orange pas prêt.
B12: Mise en service complète (tous les liens prêts) | F12: =MAX(F11,F7) -> 28 | H12: =MAX(H11,H7) -> 60 | I12: =F12/Hypothèses!$B$8 -> 5.6 | J12: =H12/Hypothèses!$B$8 -> 12 | K12: Dépend surtout du délai de l'Orange FTTO.

Sheet Hypothèses
A1: Hypothèses du projet
A2: Cellules bleues sur fond jaune = à modifier. Tout le classeur se recalcule. Montants HT.
A4: Paramètre | B4: Valeur | C4: Source / remarque
A5: TVA | B5: 0.2 | C5: Taux normal France (modifiable)
A6: Nombre d'utilisateurs | B6: 50 | C6: HYPOTHÈSE à confirmer (détermine le nombre de CAL Windows Server)
A7: Effectif de l'équipe technique | B7: 2 | C7: Personnes (1 = projet seul)
A8: Jours ouvrés par semaine | B8: 5
A9: Tarif journalier ingénieur réseau | B9: 650 | C9: € HT/jour, estimation courante en France
A10: Tarif journalier technicien | B10: 450 | C10: € HT/jour, estimation courante en France
A11: Aléas | B11: 0.1 | C11: Appliqués au matériel + installation
A12: Abonnement Orange FTTO (mensuel) | B12: 600 | C12: ESTIMATION dans la fourchette 300 à 1 700 €/mois du document fourni ; à confirmer par devis
A13: Frais d'installation des liens Internet | B13: 1750 | C13: ESTIMATION : milieu de la fourchette 0 à 3 500 € du document fourni (génie civil extérieur exclu)
A14: Postes utilisateurs supplémentaires | B14: 0 | C14: À COMPLÉTER (le diagramme prévoit 2 PC)
A15: Serveurs protégés par EDR | B15: 4 | C15: Les 4 serveurs du diagramme
A16: Postes protégés par EDR (total) | B16: =Hypothèses!$B$15+Matériel!E18+Hypothèses!$B$14 -> 6 | C16: Serveurs + postes d'accueil + postes supplémentaires
A18: Hypothèses et éléments à compléter
A19: • Périmètre : bâtiment existant, câblage et génie civil intérieur déjà réalisés (non comptés) ; génie civil extérieur exclu.
A20: • Architecture : le diagramme fourni est la référence ; 4 serveurs physiques + 1 NAS de sauvegarde (hypothèse). Supervision et journaux en VM sur le serveur .2 (hyperviseur Proxmox).
A21: • Pare-feu : OPNsense (Deciso DEC740) comme dans le diagramme ; le PDF des liens cite un Stormshield (écart à trancher).
A22: • Imprimantes : 2 imprimantes laser réseau ajoutées à la demande ; emplacement à définir ; impression via le serveur Windows (.1).
A23: • Tous les prix sont des ESTIMATIONS HT (2025-2026) à confirmer par devis, sauf les liens Internet issus du document fourni (fourchettes).
A24: • Budget « première année » = achats + installation + 12 mois d'abonnements/renouvellements. Les coûts récurrents sont isolés dans la Synthèse.
